{
  "status": "[xx]",
  "started_at": "2026-04-23T05:38:38Z",
  "last": {
    "event": "refactor.ok",
    "at": "2026-04-23T06:40:50Z"
  },
  "phase_history": [
    {
      "event": "design.ok",
      "from": "[ ]",
      "to": "[dd]",
      "at": "2026-04-23T05:38:38Z",
      "elapsed_seconds": 0
    },
    {
      "event": "build.ok",
      "from": "[dd]",
      "to": "[im]",
      "at": "2026-04-23T06:27:01Z",
      "elapsed_seconds": 2903
    },
    {
      "event": "test.ok",
      "from": "[im]",
      "to": "[ts]",
      "at": "2026-04-23T06:35:07Z",
      "elapsed_seconds": 486
    },
    {
      "event": "refactor.ok",
      "from": "[ts]",
      "to": "[xx]",
      "at": "2026-04-23T06:40:50Z",
      "elapsed_seconds": 343
    }
  ],
  "updated": "2026-04-23T06:40:50Z",
  "completed_at": "2026-04-23T06:40:50Z",
  "elapsed_seconds": 3732
}